cocodev/django/__init__.py
cocodev/django/auto_import/__init__.py
cocodev/django/auto_import/apps.py
cocodev/django/auto_import/migrations/__init__.py
django_app_auto_import-1.0.2.dist-info/LICENSE.txt
django_app_auto_import-1.0.2.dist-info/METADATA
django_app_auto_import-1.0.2.dist-info/WHEEL
django_app_auto_import-1.0.2.dist-info/top_level.txt
django_app_auto_import-1.0.2.dist-info/RECORD
