Metadata-Version: 2.1
Name: django-app-auto-import
Version: 1.0.2
Summary: Auto import a module from all yours apps!
Home-page: https://github.com/MrCocoDev/django-app-auto-import/
Author: MrCocoDev
Author-email: 3229549+MrCocoDev@users.noreply.github.com
License: MIT
Project-URL: Documentation, https://pyscaffold.org/
Platform: any
Classifier: Development Status :: 4 - Beta
Classifier: Programming Language :: Python
License-File: LICENSE.txt
Requires-Dist: django
Requires-Dist: importlib-metadata ; python_version < "3.8"
Provides-Extra: testing
Requires-Dist: setuptools ; extra == 'testing'
Requires-Dist: pytest ; extra == 'testing'
Requires-Dist: pytest-cov ; extra == 'testing'
Requires-Dist: pytest-django ; extra == 'testing'
Requires-Dist: pytest-random-order ; extra == 'testing'
